AUTHORS
BUGS.md
CHANGES.rst
LICENSE
MANIFEST.in
README.rst
TODO.md
debian8-dist.sh
setup.py
docs/.gitignore
docs/Makefile
docs/api.rst
docs/api_connection.rst
docs/api_instruction_packet.rst
docs/api_packet.rst
docs/api_status_packet.rst
docs/api_utils.rst
docs/conf.py
docs/developer.rst
docs/index.rst
docs/intro.rst
docs/make.bat
docs/images/breadboard.png
docs/images/breadboard.svg
docs/images/fritzing_sketch.fzz
docs/images/gpio_move_ok.png
docs/images/gpio_print_ok.png
docs/images/schema.png
docs/images/schema.svg
docs/xps/baudrate_115200.png
docs/xps/baudrate_19200.png
docs/xps/baudrate_9600.png
docs/xps/baudrate_measurement.png
docs/xps/baudrate_measurement_2.png
docs/xps/rdt.png
docs/xps/xps.ipynb
docs/xps/.ipynb_checkpoints/rdt-checkpoint.ipynb
docs/xps/.ipynb_checkpoints/xps-checkpoint.ipynb
examples/endless_turn.py
examples/get_temperature.py
examples/led.py
examples/move.py
examples/ping.py
examples/pretty_print_control_table.py
examples/pyax12demo
examples/scan.py
examples/set_baudrate.py
examples/set_id.py
examples/set_return_delay_time.py
pyax12/__init__.py
pyax12/argparse_default.py
pyax12/connection.py
pyax12/instruction_packet.py
pyax12/packet.py
pyax12/status_packet.py
pyax12/utils.py
pyax12.egg-info/PKG-INFO
pyax12.egg-info/SOURCES.txt
pyax12.egg-info/dependency_links.txt
pyax12.egg-info/requires.txt
pyax12.egg-info/top_level.txt
tests/test_connection.py
tests/test_instruction_packet.py
tests/test_packet.py
tests/test_status_packet.py
tests/test_utils.py