Metadata-Version: 1.1
Name: pyax12
Version: 0.5.dev3
Summary: A library to control dynamixel AX-12+ servos with python
Home-page: http://www.jdhp.org/
Author: Jeremie DECOCK
Author-email: jd.jdhp@gmail.com
License: UNKNOWN
Download-URL: http://www.jdhp.org/
Keywords: dynamixel ax12 ax-12 servo actuator library robotics
Platform: UNKNOWN
Classifier: Development Status :: 4 - Beta
Classifier: Intended Audience :: Developers
Classifier: License :: OSI Approved :: MIT License
Classifier: Natural Language :: English
Classifier: Operating System :: OS Independent
Classifier: Programming Language :: Python :: 3
Classifier: Topic :: Software Development :: Libraries
Classifier: Topic :: Software Development :: Libraries :: Python Modules
Classifier: Topic :: Software Development :: Libraries :: Application Frameworks
